mirror_soiling_data/__init__.py
mirror_soiling_data/ablrf/ablrf_20230419_20230423.xlsx
mirror_soiling_data/ablrf/ablrf_20230421_20230423.xlsx
mirror_soiling_data/ablrf/ablrf_parameters.xlsx
mirror_soiling_data/mount_isa/mount_isa_20200901_20200908.xlsx
mirror_soiling_data/mount_isa/mount_isa_20210821_20210827.xlsx
mirror_soiling_data/mount_isa/mount_isa_20220604_20220611.xlsx
mirror_soiling_data/mount_isa/mount_isa_parameters.xlsx
mirror_soiling_data/port_augusta/port_august_parameters.xlsx
mirror_soiling_data/port_augusta/port_augusta_20230826_20230901.xlsx
mirror_soiling_data/port_augusta/port_augusta_20231118_20231122.xlsx
mirror_soiling_data/qut/qut_20170807_20170811.xlsx
mirror_soiling_data/qut/qut_20170828_20170901.xlsx
mirror_soiling_data/qut/qut_20170905_20170913.xlsx
mirror_soiling_data/qut/qut_20170915_20170921.xlsx
mirror_soiling_data/qut/qut_parameters.xlsx
mirror_soiling_data/wodonga/wodonga_20220220_20220226.xlsx
mirror_soiling_data/wodonga/wodonga_20220421_20220427.xlsx
mirror_soiling_data/wodonga/wodonga_20230209_20230215.xlsx
mirror_soiling_data/wodonga/wodonga_parameters.xlsx
mirror_soiling_data-0.1.1.dist-info/licenses/LICENSE
mirror_soiling_data-0.1.1.dist-info/METADATA
mirror_soiling_data-0.1.1.dist-info/WHEEL
mirror_soiling_data-0.1.1.dist-info/top_level.txt
mirror_soiling_data-0.1.1.dist-info/RECORD
