Metadata-Version: 2.4
Name: mirror-soiling-data
Version: 0.1.1
Summary: Open-access dataset for solar mirror reflectance losses due to soiling.
Author-email: Michael Cholette <michael.cholette@qut.edu.au>, Giovanni Picotti <g.picotti@qut.edu.au>
License-Expression: MIT
Project-URL: Homepage, https://github.com/cholette/mirror_soiling_data
Project-URL: Issues, https://github.com/cholette/mirror_soiling_data/issues
Requires-Python: >=3.9
License-File: LICENSE
Dynamic: license-file
